{
    "configurations": [
        {
            "name": "Linux",
            "includePath": [
                "${workspaceFolder}/**",
                "/home/lucas/miniconda3/envs/cpp-project/include",
                "/home/lucas/miniconda3/envs/cpp-project/bin"
            ],
            "defines": [],
            "compilerPath": "/usr/bin/gcc",
            "cStandard": "c17",
            "cppStandard": "gnu++17",
            "intelliSenseMode": "linux-gcc-x64",
            "browse": {
                "path": [
                    "/home/lucas/miniconda3/envs/cpp-project/include",
                    "/home/lucas/miniconda3/envs/cpp-project/bin"
                ],
                "limitSymbolsToIncludedHeaders": true,
                "databaseFilename": ""
            }
        }
    ],
    "version": 4
}